polanalyser/__init__.py
polanalyser/container.py
polanalyser/demosaicing.py
polanalyser/mueller.py
polanalyser/stokes.py
polanalyser/visualization.py
polanalyser/io/__init__.py
polanalyser/io/image_io.py
polanalyser/io/json_io.py
polanalyser/sympy/__init__.py
polanalyser/sympy/mueller.py
polanalyser/sympy/stokes.py
polanalyser-3.0.0.dist-info/LICENSE
polanalyser-3.0.0.dist-info/METADATA
polanalyser-3.0.0.dist-info/WHEEL
polanalyser-3.0.0.dist-info/top_level.txt
polanalyser-3.0.0.dist-info/RECORD
